hcli_hc/__init__.py
hcli_hc/__main__.py
hcli_hc/config.py
hcli_hc/hutils.py
hcli_hc/package.py
hcli_hc/cli/__init__.py
hcli_hc/cli/cli.py
hcli_hc/cli/error.py
hcli_hc/cli/jobqueue.py
hcli_hc/cli/jogger.py
hcli_hc/cli/locker.py
hcli_hc/cli/logger.py
hcli_hc/cli/service.py
hcli_hc/cli/streamer.py
hcli_hc/cli/template.json
hcli_hc/cli/grbl/__init__.py
hcli_hc/cli/grbl/controller.py
hcli_hc/cli/grbl/device.py
hcli_hc/cli/grbl/nudger.py
hcli_hc/data/hcli_hc.1
hcli_hc-0.5.1.dist-info/LICENSE.txt
hcli_hc-0.5.1.dist-info/METADATA
hcli_hc-0.5.1.dist-info/WHEEL
hcli_hc-0.5.1.dist-info/entry_points.txt
hcli_hc-0.5.1.dist-info/top_level.txt
hcli_hc-0.5.1.dist-info/RECORD
