Metadata-Version: 2.2
Name: hcli_hc
Version: 0.5.1
Summary: HCLI hc is a pypi wrapper that contains an HCLI sample application (hc); hc can can act both as a gcode streamer (e.g. for OpenBuilds Blackbox controller v1.1g) and CNC interface. In other words, this HCLI acts in the same capacity as the OpenBuilds CONTROL software or OpenBuilds Interface CNC Touch hardware to help control a GRBL v1.1g controlled CNC.
Author-email: Jeff Michaud <cometaj2@proton.me>
License: MIT
Project-URL: Homepage, https://github.com/cometaj2/hcli_hc
Keywords: cli,client,server,connector,hypermedia,rest,generic,development
Classifier: Development Status :: 2 - Pre-Alpha
Classifier: Intended Audience :: Developers
Classifier: Topic :: Software Development
Classifier: License :: OSI Approved :: MIT License
Classifier: Programming Language :: Python :: 3.8
Classifier: Programming Language :: Python :: 3.9
Classifier: Programming Language :: Python :: 3.10
Classifier: Programming Language :: Python :: 3.11
Classifier: Programming Language :: Python :: 3.12
License-File: LICENSE.txt
Requires-Dist: apscheduler==3.11.0
Requires-Dist: pyserial==3.5
